FalApp/__init__.py
FalApp/myfunctions.py
tests/__init__.py
tests/test_myfunctions.py
FalLib-0.1.0.dist-info/METADATA
FalLib-0.1.0.dist-info/WHEEL
FalLib-0.1.0.dist-info/top_level.txt
FalLib-0.1.0.dist-info/RECORD
