Metadata-Version: 2.1
Name: FalLib
Version: 0.1.0
Summary: Fareed Library for creating apps of FALAFEL
Home-page: https://github.com/yourusername/your-library
Author: Fareed
Author-email: fareed@falafel.com
Classifier: Programming Language :: Python :: 3
Classifier: License :: OSI Approved :: MIT License
Classifier: Operating System :: OS Independent
Requires-Python: >=3.6
